comrun/__init__.py
comrun/comrun.py
comrun/datatypes.py
comrun/errors.py
comrun-0.3.2.dist-info/WHEEL
comrun-0.3.2.dist-info/METADATA
comrun-0.3.2.dist-info/RECORD
