Metadata-Version: 2.3
Name: comrun
Version: 0.3.2
Summary: Simplified and configurable wrapper for Python's subprocess.Popen
Author: Yevhen Bondarenko
Author-email: Yevhen Bondarenko <zekbond@gmail.com>
License: MIT
Requires-Dist: rich>=14.2.0
Requires-Python: >=3.10
Project-URL: Documentation, https://jgroxz.github.io/comrun/
Project-URL: Homepage, https://github.com/jgroxz/comrun
Project-URL: Repository, https://github.com/jgroxz/comrun
